django_invoke/__init__.py
django_invoke/_config.py
django_invoke/django.py
django_invoke/docker.py
django_invoke/printer.py
django_invoke/py.typed
django_invoke/python.py
django_invoke-0.0.0.dev2.dist-info/METADATA
django_invoke-0.0.0.dev2.dist-info/WHEEL
django_invoke-0.0.0.dev2.dist-info/top_level.txt
django_invoke-0.0.0.dev2.dist-info/RECORD
